{
  "$schema": "https://jsr.io/schema/config-file.v1.json",
  "name": "@mainz/cli-deno",
  "version": "0.1.0-alpha.78",
  "license": "MIT",
  "compilerOptions": {
    "lib": [
      "dom",
      "deno.ns",
      "es2022"
    ],
    "strict": true
  },
  "imports": {
    "happy-dom": "npm:happy-dom@20.9.0",
    "typescript": "npm:typescript@5.9.3",
    "vite": "npm:vite@8.0.16"
  },
  "exports": {
    ".": "./mod.cli-deno.ts"
  },
  "publish": {
    "include": [
      "LICENSE",
      "README.cli-deno.md",
      "CLI-SPEC.md",
      "mod.cli-deno.ts",
      "src/**",
      "templates/**"
    ],
    "exclude": [
      "**/tests/**",
      "src/tests/**",
      "**/*.fixture.ts",
      "**/*.fixture.tsx",
      "**/_template.*"
    ]
  }
}
